tapis_cli/__about__.py
tapis_cli/__init__.py
tapis_cli/constants.py
tapis_cli/display.py
tapis_cli/firstrun.py
tapis_cli/githelper.py
tapis_cli/main.py
tapis_cli/user_agent.py
tapis_cli/utils.py
tapis_cli/clients/__init__.py
tapis_cli/clients/http.py
tapis_cli/clients/basic/__init__.py
tapis_cli/clients/basic/main.py
tapis_cli/clients/nonce/__init__.py
tapis_cli/clients/nonce/main.py
tapis_cli/clients/oauth/__init__.py
tapis_cli/clients/oauth/bearer.py
tapis_cli/clients/oauth/impersonate.py
tapis_cli/clients/oauth/keysecret.py
tapis_cli/clients/oauth/refresh.py
tapis_cli/clients/services/__init__.py
tapis_cli/clients/services/mixins.py
tapis_cli/clients/services/taccapis/__init__.py
tapis_cli/clients/services/taccapis/v1/__init__.py
tapis_cli/clients/services/taccapis/v2/__init__.py
tapis_cli/clients/services/taccapis/v2/api_keysecret.py
tapis_cli/clients/services/taccapis/v2/apiclient.py
tapis_cli/clients/services/taccapis/v2/base.py
tapis_cli/clients/services/taccapis/v2/basic.py
tapis_cli/clients/services/taccapis/v2/bearer.py
tapis_cli/clients/services/taccapis/v2/bearer_refresh.py
tapis_cli/clients/services/taccapis/v2/direct.py
tapis_cli/clients/services/taccapis/v2/format_many.py
tapis_cli/clients/services/taccapis/v2/format_one.py
tapis_cli/clients/services/taccapis/v3/__init__.py
tapis_cli/commands/__init__.py
tapis_cli/commands/gitlab/__init__.py
tapis_cli/commands/gitlab/v4/__init__.py
tapis_cli/commands/local/__init__.py
tapis_cli/commands/local/statuses.py
tapis_cli/commands/local/variables.py
tapis_cli/commands/local/versions.py
tapis_cli/commands/local/settings/__init__.py
tapis_cli/commands/local/settings/get.py
tapis_cli/commands/local/settings/list.py
tapis_cli/commands/local/settings/mixins.py
tapis_cli/commands/local/settings/set.py
tapis_cli/commands/local/settings/unset.py
tapis_cli/commands/registry/__init__.py
tapis_cli/commands/registry/v2/__init__.py
tapis_cli/commands/taccapis/__init__.py
tapis_cli/commands/taccapis/__model.py
tapis_cli-1.0.6.dist-info/AUTHORS
tapis_cli-1.0.6.dist-info/LICENSE.txt
tapis_cli-1.0.6.dist-info/METADATA
tapis_cli-1.0.6.dist-info/NOTICE.txt
tapis_cli-1.0.6.dist-info/WHEEL
tapis_cli-1.0.6.dist-info/entry_points.txt
tapis_cli-1.0.6.dist-info/top_level.txt
tapis_cli-1.0.6.dist-info/RECORD
