Metadata-Version: 2.1
Name: tapis-cli
Version: 1.0.6
Summary: Scripting interface to the Tapis platform. Documentation at https://tapis-cli.rtfd.io/
Home-page: https://github.com/TACC-Cloud/tapis-cli
Author: Matthew Vaughn, Erik Ferlanti, John Fonner, William Allen, Joshua Urrutia, Ethan Ho, Shweta Gopaulakrishna
Author-email: "TACC Opensource" <opensource@tacc.cloud>
Maintainer-email: "TACC Help" <help@tacc.cloud>
License: LICENSE.txt
Keywords: faas, rest, web service, openapi, swagger, serverless
Platform: UNKNOWN
Classifier: Development Status :: 5 - Production/Stable
Classifier: Intended Audience :: Developers
Classifier: Intended Audience :: Science/Research
Classifier: License :: OSI Approved :: BSD License
Classifier: Operating System :: OS Independent
Classifier: Programming Language :: Python :: 3
Classifier: Programming Language :: Python :: 3.5
Classifier: Programming Language :: Python :: 3.6
Classifier: Programming Language :: Python :: 3.7
Classifier: Programming Language :: Python :: 3.8
License-File: LICENSE.txt
License-File: NOTICE.txt
License-File: AUTHORS
Requires-Dist: arrow
Requires-Dist: cliff
Requires-Dist: colorama
Requires-Dist: configparser
Requires-Dist: curlify
Requires-Dist: dateparser
Requires-Dist: docker (<=4.2.0)
Requires-Dist: pathlib2
Requires-Dist: pbr
Requires-Dist: PyGithub
Requires-Dist: pymongo
Requires-Dist: python-dotenv
Requires-Dist: python-slugify
Requires-Dist: stevedore
Requires-Dist: stringcase
Requires-Dist: tacc-cookiecutter
Requires-Dist: tenacity
Requires-Dist: validators
Requires-Dist: agavepy (==1.0.0a11)
